hdmpy/LassoShooting_fit.py
hdmpy/__init__.py
hdmpy/help_functions.py
hdmpy/rlasso.py
hdmpy/rlassoEffects.py
hdmpy-0.1.0.dist-info/METADATA
hdmpy-0.1.0.dist-info/WHEEL
hdmpy-0.1.0.dist-info/licenses/LICENSE
hdmpy-0.1.0.dist-info/RECORD
