Metadata-Version: 2.4
Name: hdmpy
Version: 0.1.0
Summary: Python port of parts of the R package hdm (High-Dimensional Metrics)
Project-URL: Homepage, https://github.com/maxhuppertz/hdmpy
Project-URL: Repository, https://github.com/maxhuppertz/hdmpy
Author: Original R authors: hdm team, Python port: Maximilian Huppertz
License: MIT License
License-File: LICENSE
Keywords: econometrics,hdm,high-dimensional,lasso,statistics
Classifier: Development Status :: 3 - Alpha
Classifier: Intended Audience :: Science/Research
Classifier: License :: OSI Approved :: MIT License
Classifier: Programming Language :: Python
Classifier: Programming Language :: Python :: 3
Classifier: Programming Language :: Python :: 3 :: Only
Classifier: Programming Language :: Python :: 3.8
Classifier: Programming Language :: Python :: 3.9
Classifier: Programming Language :: Python :: 3.10
Classifier: Programming Language :: Python :: 3.11
Classifier: Programming Language :: Python :: 3.12
Classifier: Topic :: Scientific/Engineering
Requires-Python: >=3.8
Requires-Dist: joblib>=1.0
Requires-Dist: multiprocess>=0.70
Requires-Dist: numpy>=1.20
Requires-Dist: pandas>=1.0
Requires-Dist: scikit-learn>=1.0
Requires-Dist: scipy>=1.7
Provides-Extra: dev
Requires-Dist: build>=1.2; extra == 'dev'
Requires-Dist: pytest>=7.0; extra == 'dev'
Requires-Dist: twine>=5.0; extra == 'dev'
